reqargs/__init__.py
reqargs/__main__.py
reqargs/colorls.py
reqargs/reqargs.py
argsreq-1.8.dist-info/METADATA
argsreq-1.8.dist-info/WHEEL
argsreq-1.8.dist-info/top_level.txt
argsreq-1.8.dist-info/RECORD
