Metadata-Version: 2.1
Name: argsreq
Version: 1.8
Summary: install all requirements
Author: akkam222
Author-email: ahmedakkam@gmail.com
Keywords: python
Classifier: Programming Language :: Python :: 3
Classifier: Operating System :: Microsoft :: Windows
